{"1001": {"Manufacture_Date": "1 dec 2020", "Product_Name": "Samsung Galaxy M21", "Product_Price": "12999", "Product_Discount('%')": "10", "Product_Quantity": "0", "Product_Category": "Mobiles"}, "1002": {"Manufacture_Date": "2 dec 2020", "Product_Name": "Dell 3593", "Product_Price": "62500", "Product_Discount('%')": "10", "Product_Quantity": "3", "Product_Category": "Laptops"}, "1003": {"Manufacture_Date": "3 dec 202", "Product_Name": "Sony", "Product_Price": "9999", "Product_Discount('%')": "5", "Product_Quantity": "9", "Product_Category": "Headphones"}, "1004": {"Manufacture_Date": "4 jan 2021", "Product_Name": "Canon", "Product_Price": "15999", "Product_Discount('%')": "5", "Product_Quantity": "5", "Product_Category": "Cameras"}, "1005": {"Manufacture_Date": "5 jan 2021", "Product_Name": "Redmi 9", "Product_Price": "11599", "Product_Discount('%')": "5", "Product_Quantity": "9", "Product_Category": "Mobiles"}, "1006": {"Manufacture_Date": "6 jan 2021", "Product_Name": "Hp 1050", "Product_Price": "69999", "Product_Discount('%')": "10", "Product_Quantity": "10", "Product_Category": "Laptops"}, "1007": {"Manufacture_Date": "7 jan 2021", "Product_Name": "Phillips", "Product_Price": "31999", "Product_Discount('%')": "10", "Product_Quantity": "25", "Product_Category": "Headphones"}, "1008": {"Manufacture_Date": "6 feb 2021", "Product_Name": "Nikon", "Product_Price": "29999", "Product_Discount('%')": "7", "Product_Quantity": "20", "Product_Category": "Cameras"}, "1009": {"Manufacture_Date": "8 feb 2021", "Product_Name": "Iphone 9", "Product_Price": "27999", "Product_Discount('%')": "10", "Product_Quantity": "4", "Product_Category": "Mobiles"}, "1010": {"Manufacture_Date": "9 march 2021", "Product_Name": "Apple", "Product_Price": "56999", "Product_Discount('%')": "12", "Product_Quantity": "10", "Product_Category": "Laptops"}, "1011": {"Manufacture_Date": "10 march 2021", "Product_Name": "Sennheiser", "Product_Price": "999", "Product_Discount('%')": "2", "Product_Quantity": "20", "Product_Category": "Headphones"}, "1012": {"Manufacture_Date": "11 april 2021", "Product_Name": "Canon 1300D", "Product_Price": "19999", "Product_Discount('%')": "10", "Product_Quantity": "20", "Product_Category": "Cameras"}, "1013": {"Manufacture_Date": "12 april 2021", "Product_Name": "Hp-14", "Product_Price": "55999", "Product_Discount('%')": "10", "Product_Quantity": "2", "Product_Category": "Laptops"}, "1014": {"Manufacture_Date": "5 april 2021", "Product_Name": "Dell-1500", "Product_Price": "47999", "Product_Discount('%')": "0", "Product_Quantity": "3", "Product_Category": "Laptops"}, "1015": {"Manufacture_Date": "3 may 2021", "Product_Name": "Dell-inspiron", "Product_Price": "55999", "Product_Discount('%')": "10", "Product_Quantity": "10", "Product_Category": "Laptops"}, "1016": {"Manufacture_Date": "13 may 2021", "Product_Name": "Dell-12", "Product_Price": "69999", "Product_Discount('%')": "12", "Product_Quantity": "15", "Product_Category": "Laptops"}, "1017": {"Manufacture_Date": "15 may 2021", "Product_Name": "MacBook", "Product_Price": "75999", "Product_Discount('%')": "10", "Product_Quantity": "30", "Product_Category": "Laptops"}, "1018": {"Manufacture_Date": "9 june 2021", "Product_Name": "Asus", "Product_Price": "43999", "Product_Discount('%')": "9", "Product_Quantity": "15", "Product_Category": "Laptops"}, "1019": {"Manufacture_Date": "19 june 2021", "Product_Name": "Lenovo", "Product_Price": "55599", "Product_Discount('%')": "10", "Product_Quantity": "10", "Product_Category": "Laptops"}, "1020": {"Manufacture_Date": "27 sept 2021", "Product_Name": "Acer", "Product_Price": "35999", "Product_Discount('%')": "0", "Product_Quantity": "25", "Product_Category": "Laptops"}, "1021": {"Manufacture_Date": "19 june 2021", "Product_Name": "Sony ", "Product_Price": "7490", "Product_Discount('%')": "0", "Product_Quantity": "30", "Product_Category": "Headphones"}, "1022": {"Manufacture_Date": "5 july 2021", "Product_Name": "Sennheiser", "Product_Price": "999", "Product_Discount('%')": "8", "Product_Quantity": "10", "Product_Category": "Headphones"}, "1023": {"Manufacture_Date": "17 july 2021", "Product_Name": "Sennheiser ", "Product_Price": "7490", "Product_Discount('%')": "0", "Product_Quantity": "30", "Product_Category": "Headphones"}, "1024": {"Manufacture_Date": "24 july 2021", "Product_Name": "boAT", "Product_Price": "1190", "Product_Discount('%')": "5", "Product_Quantity": "10", "Product_Category": "Headphones"}, "1025": {"Manufacture_Date": "3 august 2021", "Product_Name": "Phillips", "Product_Price": "8490", "Product_Discount('%')": "10", "Product_Quantity": "20", "Product_Category": "Headphones"}, "1026": {"Manufacture_Date": "11 august 2021", "Product_Name": "Canon ", "Product_Price": "34599", "Product_Discount('%')": "12", "Product_Quantity": "20", "Product_Category": "Cameras"}, "1027": {"Manufacture_Date": "12 august 2021", "Product_Name": "Canon ", "Product_Price": "33399", "Product_Discount('%')": "2", "Product_Quantity": "30", "Product_Category": "Cameras"}, "1028": {"Manufacture_Date": "12 sept 2021", "Product_Name": "Canon ", "Product_Price": "32999", "Product_Discount('%')": "5", "Product_Quantity": "20", "Product_Category": "Cameras"}, "1029": {"Manufacture_Date": "22 sept 2021", "Product_Name": "Nikon ", "Product_Price": "30499", "Product_Discount('%')": "10", "Product_Quantity": "35", "Product_Category": "Cameras"}, "1030": {"Manufacture_Date": "19 sept 2021", "Product_Name": "Nikon ", "Product_Price": "4200", "Product_Discount('%')": "5", "Product_Quantity": "20", "Product_Category": "Cameras"}, "1031": {"Product_Name": "Poco 3 Pro", "Product_Price": "12999", "Product_Discount('%')": "10", "Product_Quantity": "12", "Product_Category": "Mobiles", "Manufacture_Date": "23 sept 2021"}}